ci_info/__init__.py
ci_info/_version.py
ci_info/vendors.json
ci_info/tests/__init__.py
ci_info/tests/test_circle.py
ci_info/tests/test_gha.py
ci_info/tests/test_travis.py
ci_info-0.3.0.dist-info/LICENSE
ci_info-0.3.0.dist-info/METADATA
ci_info-0.3.0.dist-info/WHEEL
ci_info-0.3.0.dist-info/top_level.txt
ci_info-0.3.0.dist-info/RECORD
