Metadata-Version: 2.1
Name: ci-info
Version: 0.3.0
Summary: Continuous Integration Information
Home-page: https://github.com/mgxd/ci-info
Author: Mathias Goncalves
Author-email: mathiasg@mit.edu
License: MIT
Classifier: Development Status :: 3 - Alpha
Classifier: Intended Audience :: Developers
Classifier: License :: OSI Approved :: Apache Software License
Classifier: Programming Language :: Python :: 3.7
Classifier: Programming Language :: Python :: 3.8
Classifier: Programming Language :: Python :: 3.9
Classifier: Programming Language :: Python :: 3.10
Provides: ci_info
Requires-Python: >=3.7
Provides-Extra: test
Provides-Extra: tests
Provides-Extra: all
License-File: LICENSE
